nexosim/__init__.py
nexosim/_config.py
nexosim/_simulation.py
nexosim/exceptions.py
nexosim/time.py
nexosim/types.py
nexosim/_proto/simulation.proto
nexosim/_proto/simulation_pb2.py
nexosim/_proto/simulation_pb2.pyi
nexosim/_proto/simulation_pb2_grpc.py
nexosim/_proto/simulation_pb2_grpc.pyi
nexosim/aio/__init__.py
nexosim/aio/_simulation.py
nexosim_py-0.1.0.dist-info/METADATA
nexosim_py-0.1.0.dist-info/WHEEL
nexosim_py-0.1.0.dist-info/licenses/LICENSE
nexosim_py-0.1.0.dist-info/RECORD
