Metadata-Version: 2.4
Name: NeXosim-py
Version: 0.1.0
Summary: A gRPC client for the NeXosim simulator
Project-URL: Source, https://github.com/asynchronics/nexosim-py
Project-URL: Issues, https://github.com/asynchronics/nexosim-py/issues
Project-URL: Documentation, https://nexosim-py.readthedocs.io
Maintainer-email: Stanisław Massalski <stanislaw.massalski@asynchronics.com>
License-Expression: Apache-2.0
License-File: LICENSE
Classifier: License :: OSI Approved :: Apache Software License
Classifier: Operating System :: OS Independent
Classifier: Programming Language :: Python :: 3
Requires-Python: >=3.11
Requires-Dist: attrs>=23.1.0
Requires-Dist: cattrs>=24.1.0
Requires-Dist: cbor2>=5.4.6
Requires-Dist: grpcio>=1.0.0
Requires-Dist: protobuf<6,>=5.29.2
Requires-Dist: typing-extensions>=4.12.2
